Metadata-Version: 2.1
Name: gpiopico
Version: 1.0.0
Summary: Easy way to connect hardware and use gpio in raspberry pico
Home-page: https://github.com/irvyncornejo/hwlib/tree/main/raspberry-pico/rpi-gpio-pico
Author: Irvyn Cornejo
Author-email: irvyncornejo@gmail.com
License: MIT
Keywords: raspberry-pi pico,rpi-pico
Platform: UNKNOWN
Classifier: Development Status :: 3 - Alpha
Classifier: Intended Audience :: Developers
Classifier: Topic :: Software Development :: Build Tools
Classifier: License :: OSI Approved :: MIT License
Classifier: Programming Language :: Python :: 3
License-File: LICENSE.txt
